celery_tasks/CeleryApp.py
celery_tasks/CeleryConfig.py
celery_tasks/__init__.py
celery_tasks/tasks.py
celery_tasks/utils/ExecuteTask.py
core_base/.DS_Store
core_base/__init__.py
core_base/dispatch.py
core_base/settings.py
core_base/start_safety.sh
core_base/websocketConfig.py
core_base/system/.DS_Store
core_base/system/__init__.py
core_base/system/admin.py
core_base/system/apps.py
core_base/system/models.py
core_base/system/models_safe_field.py
core_base/system/signals.py
core_base/system/tests.py
core_base/system/urls.py
core_base/system/fixtures/__init__.py
core_base/system/fixtures/init_apiwhitelist.json
core_base/system/fixtures/init_dept.json
core_base/system/fixtures/init_dictionary.json
core_base/system/fixtures/init_menu.json
core_base/system/fixtures/init_role.json
core_base/system/fixtures/init_systemconfig.json
core_base/system/fixtures/init_users.json
core_base/system/fixtures/initialize.py
core_base/system/management/__init__.py
core_base/system/management/commands/__init__.py
core_base/system/management/commands/generate_init_json.py
core_base/system/management/commands/init.py
core_base/system/management/commands/init_area.py
core_base/system/migrations/0001_initial.py
core_base/system/migrations/__init__.py
core_base/system/util/__init__.py
core_base/system/util/pca-code.json
core_base/system/views/__init__.py
core_base/system/views/api_white_list.py
core_base/system/views/area.py
core_base/system/views/datav.py
core_base/system/views/dept.py
core_base/system/views/dictionary.py
core_base/system/views/file_list.py
core_base/system/views/login.py
core_base/system/views/login_log.py
core_base/system/views/menu.py
core_base/system/views/menu_button.py
core_base/system/views/message_center.py
core_base/system/views/operation_log.py
core_base/system/views/role.py
core_base/system/views/system_config.py
core_base/system/views/task_management.py
core_base/system/views/ueditor_settings.py
core_base/system/views/user.py
core_base/templates/__init__.py
core_base-1.2.2.dist-info/LICENSE
core_base-1.2.2.dist-info/METADATA
core_base-1.2.2.dist-info/WHEEL
core_base-1.2.2.dist-info/top_level.txt
core_base-1.2.2.dist-info/RECORD
