Metadata-Version: 2.1
Name: core-base
Version: 1.2.2
Summary: 处理Django Rbac权限,日志等
Home-page: http://congxing.wang
Author: cx
Author-email: 2256807897@qq.com
License: MIT
Project-URL: Bug Tracker, http://congxing.wang
Classifier: Programming Language :: Python :: 3
Classifier: License :: OSI Approved :: MIT License
Classifier: Operating System :: OS Independent
Requires-Python: >=3.9
License-File: LICENSE
Requires-Dist: Django >=4.2.0
Requires-Dist: Pillow >=9.4.0
Requires-Dist: django-cors-headers >=3.11.0
Requires-Dist: django-filter >=21.1
Requires-Dist: djangorestframework >=3.14.0
Requires-Dist: djangorestframework-simplejwt >=5.2.2
Requires-Dist: requests >=2.28.1
Requires-Dist: six >=1.16.0
Requires-Dist: user-agents >=2.2.0
Requires-Dist: django-restql >=0.15.2
Requires-Dist: openpyxl >=3.0.10
Requires-Dist: pypinyin >=0.47.1
Requires-Dist: django-simple-captcha >=0.4
Requires-Dist: django-timezone-field >=1.0
Requires-Dist: pandas >=1.1.3
Requires-Dist: pycryptodome >=3.15.0
Requires-Dist: django-celery-beat >=2.5.0
Requires-Dist: django-celery-results >=2.5.1
Requires-Dist: django-comment-migrate >=0.1.7
Requires-Dist: django-simple-captcha >=0.5.17
Requires-Dist: channels >=3.0.5
Requires-Dist: channels-redis >=3.4.1
Requires-Dist: mysqlclient >=2.2.0
Requires-Dist: safety >=2.3.5
